commercecraft_utils/__init__.py
commercecraft_utils/translation_engine.py
commercecraft_utils/translation_processor.py
commercecraft_utils/translation_service.py
commercecraft_utils/utils.py
commercecraft_utils-0.1.6.dist-info/LICENSE
commercecraft_utils-0.1.6.dist-info/METADATA
commercecraft_utils-0.1.6.dist-info/WHEEL
commercecraft_utils-0.1.6.dist-info/top_level.txt
commercecraft_utils-0.1.6.dist-info/RECORD
