Metadata-Version: 2.2
Name: commercecraft-utils
Version: 0.1.6
Summary: A Python utility for translating CSV files between different languages using OpenAI's API
Author-email: SkhaS <ehz.skhas@gmail.com>
License: MIT License
Project-URL: Homepage, https://github.com/ehzSkhaS/commercecraft-utils
Project-URL: Documentation, https://github.com/ehzSkhaS/commercecraft-utils#readme
Project-URL: Issues, https://github.com/ehzSkhaS/commercecraft-utils/issues
Classifier: Programming Language :: Python :: 3
Classifier: License :: OSI Approved :: MIT License
Classifier: Operating System :: OS Independent
Classifier: Development Status :: 4 - Beta
Classifier: Intended Audience :: Developers
Classifier: Topic :: Text Processing :: Linguistic
Requires-Python: >=3.8
License-File: LICENSE
Requires-Dist: openai>=1.0.0
Requires-Dist: pandas>=1.3.0
Requires-Dist: pydantic>=2.0.0
Requires-Dist: emoji>=2.2.0
Requires-Dist: regex>=2023.0.0
